LICENSE
README.md
setup.py
cloudpods/__init__.py
cloudpods/cloudpods.py
python3_cloudpods.egg-info/PKG-INFO
python3_cloudpods.egg-info/SOURCES.txt
python3_cloudpods.egg-info/dependency_links.txt
python3_cloudpods.egg-info/requires.txt
python3_cloudpods.egg-info/top_level.txt